{
  "main": {
    "id": "df405147f21e1c2a",
    "type": "split",
    "children": [
      {
        "id": "8e52d4d1c179ab07",
        "type": "tabs",
        "children": [
          {
            "id": "439f59e2b511eb96",
            "type": "leaf",
            "state": {
              "type": "markdown",
              "state": {
                "file": "the-lazarus-file-main.md",
                "mode": "source",
                "source": false
              }
            }
          },
          {
            "id": "2f1b29d15981bcc4",
            "type": "leaf",
            "state": {
              "type": "markdown",
              "state": {
                "file": "people.md",
                "mode": "source",
                "source": false
              }
            }
          },
          {
            "id": "b392e9d0dc49695f",
            "type": "leaf",
            "state": {
              "type": "markdown",
              "state": {
                "file": "targets.md",
                "mode": "source",
                "source": false
              }
            }
          }
        ],
        "currentTab": 2
      }
    ],
    "direction": "vertical"
  },
  "left": {
    "id": "8b3f1eb07f028353",
    "type": "split",
    "children": [
      {
        "id": "7a7735a4c0a6b855",
        "type": "tabs",
        "children": [
          {
            "id": "53c4be2e1b8602cc",
            "type": "leaf",
            "state": {
              "type": "file-explorer",
              "state": {
                "sortOrder": "alphabetical"
              }
            }
          },
          {
            "id": "61f7ce9a2a2d52d5",
            "type": "leaf",
            "state": {
              "type": "search",
              "state": {
                "query": "",
                "matchingCase": false,
                "explainSearch": false,
                "collapseAll": false,
                "extraContext": false,
                "sortOrder": "alphabetical"
              }
            }
          },
          {
            "id": "2fcb70e73395947b",
            "type": "leaf",
            "state": {
              "type": "bookmarks",
              "state": {}
            }
          }
        ]
      }
    ],
    "direction": "horizontal",
    "width": 300
  },
  "right": {
    "id": "087fbba9238b1488",
    "type": "split",
    "children": [
      {
        "id": "d24b78a72db8e366",
        "type": "tabs",
        "children": [
          {
            "id": "47f5f40ddbda66eb",
            "type": "leaf",
            "state": {
              "type": "backlink",
              "state": {
                "file": "targets.md",
                "collapseAll": false,
                "extraContext": false,
                "sortOrder": "alphabetical",
                "showSearch": false,
                "searchQuery": "",
                "backlinkCollapsed": false,
                "unlinkedCollapsed": true
              }
            }
          },
          {
            "id": "012eac8f799cd28d",
            "type": "leaf",
            "state": {
              "type": "outgoing-link",
              "state": {
                "file": "targets.md",
                "linksCollapsed": false,
                "unlinkedCollapsed": true
              }
            }
          },
          {
            "id": "0757cef1734d225e",
            "type": "leaf",
            "state": {
              "type": "tag",
              "state": {
                "sortOrder": "frequency",
                "useHierarchy": true
              }
            }
          },
          {
            "id": "03eadd96860a1041",
            "type": "leaf",
            "state": {
              "type": "outline",
              "state": {
                "file": "targets.md"
              }
            }
          }
        ]
      }
    ],
    "direction": "horizontal",
    "width": 300,
    "collapsed": true
  },
  "left-ribbon": {
    "hiddenItems": {
      "switcher:Open quick switcher": false,
      "graph:Open graph view": false,
      "canvas:Create new canvas": false,
      "daily-notes:Open today's daily note": false,
      "templates:Insert template": false,
      "command-palette:Open command palette": false
    }
  },
  "active": "b392e9d0dc49695f",
  "lastOpenFiles": [
    "the-lazarus-file-main.md",
    "targets.md",
    "people.md",
    "media",
    "Welcome.md"
  ]
}